geot/__init__.py
geot/partialot.py
geot/plotting.py
geot/sinkhorn_loss.py
tests/test_partial_ot.py
tests/test_sinkhorn_loss.py
geot-0.1.0.dist-info/LICENSE
geot-0.1.0.dist-info/METADATA
geot-0.1.0.dist-info/WHEEL
geot-0.1.0.dist-info/top_level.txt
geot-0.1.0.dist-info/RECORD
