Metadata-Version: 2.1
Name: geot
Version: 0.1.0
Summary: Optimal Transport metrics for evaluating spatiotemporal predictions
License: MIT License
Keywords: geographic,geospatial,optimal transport,spatiotemporal,metrics,evaluation
Classifier: Programming Language :: Python :: 3
Classifier: License :: OSI Approved :: MIT License
Classifier: Operating System :: OS Independent
Requires-Python: >=3.9
License-File: LICENSE
Requires-Dist: geomloss>=0.2.3
Requires-Dist: numpy>=1.21.0
Requires-Dist: pytest
Requires-Dist: wurlitzer>=3.1.0
Requires-Dist: wasserstein>=1.1.0
Requires-Dist: scipy>=1.8.0
Requires-Dist: matplotlib>=3.5.0
Requires-Dist: pandas>=1.5.3
Requires-Dist: POT>=0.9.0
Requires-Dist: notebook>=6.4.0
